tensorflow_graphics/__init__.py
tensorflow_graphics/datasets/__init__.py
tensorflow_graphics/datasets/features/__init__.py
tensorflow_graphics/datasets/features/camera_feature.py
tensorflow_graphics/datasets/features/camera_feature_test.py
tensorflow_graphics/datasets/features/pose_feature.py
tensorflow_graphics/datasets/features/pose_feature_test.py
tensorflow_graphics/datasets/features/trimesh_feature.py
tensorflow_graphics/datasets/features/trimesh_feature_test.py
tensorflow_graphics/datasets/features/voxel_feature.py
tensorflow_graphics/datasets/features/voxel_feature_test.py
tensorflow_graphics/datasets/modelnet40/__init__.py
tensorflow_graphics/datasets/modelnet40/modelnet40.py
tensorflow_graphics/datasets/modelnet40/modelnet40_checksums.py
tensorflow_graphics/datasets/modelnet40/modelnet40_makefakes.py
tensorflow_graphics/datasets/modelnet40/modelnet40_run.py
tensorflow_graphics/datasets/modelnet40/modelnet40_show.py
tensorflow_graphics/datasets/modelnet40/modelnet40_test.py
tensorflow_graphics/datasets/pix3d/__init__.py
tensorflow_graphics/datasets/pix3d/pix3d.py
tensorflow_graphics/datasets/pix3d/pix3d_test.py
tensorflow_graphics/datasets/shapenet/__init__.py
tensorflow_graphics/datasets/shapenet/shapenet.py
tensorflow_graphics/datasets/shapenet/shapenet_test.py
tensorflow_graphics/datasets/testing/__init__.py
tensorflow_graphics/geometry/__init__.py
tensorflow_graphics/geometry/convolution/__init__.py
tensorflow_graphics/geometry/convolution/graph_convolution.py
tensorflow_graphics/geometry/convolution/graph_pooling.py
tensorflow_graphics/geometry/convolution/utils.py
tensorflow_graphics/geometry/convolution/tests/__init__.py
tensorflow_graphics/geometry/convolution/tests/graph_convolution_test.py
tensorflow_graphics/geometry/convolution/tests/graph_pooling_test.py
tensorflow_graphics/geometry/convolution/tests/utils_test.py
tensorflow_graphics/geometry/deformation_energy/__init__.py
tfg_nightly-2022.7.23.dist-info/LICENSE
tfg_nightly-2022.7.23.dist-info/METADATA
tfg_nightly-2022.7.23.dist-info/WHEEL
tfg_nightly-2022.7.23.dist-info/top_level.txt
tfg_nightly-2022.7.23.dist-info/RECORD
