Metadata-Version: 2.1
Name: tfg-nightly
Version: 2022.7.23
Summary: A library that contains well defined, reusable and cleanly written graphics related ops and utility functions for TensorFlow.
Home-page: https://github.com/tensorflow/graphics
Author: Google LLC
Author-email: tf-graphics-eng@google.com
License: Apache 2.0
Keywords: machine learning,tensorflow,graphics,geometry,3D
Classifier: Development Status :: 5 - Production/Stable
Classifier: Programming Language :: Python :: 3
Classifier: Topic :: Scientific/Engineering :: Mathematics
Classifier: Topic :: Scientific/Engineering :: Artificial Intelligence
License-File: LICENSE
Requires-Dist: tensorflow (>=2.2.0)
Requires-Dist: tensorflow-addons (>=0.10.0)
Requires-Dist: tensorflow-datasets (>=2.0.0)
Requires-Dist: absl-py (>=0.6.1)
Requires-Dist: h5py (>=2.10.0)
Requires-Dist: matplotlib (>=2.2.5)
Requires-Dist: numpy (>=1.15.4)
Requires-Dist: psutil (>=5.7.0)
Requires-Dist: scipy (>=1.1.0)
Requires-Dist: tqdm (>=4.45.0)
Requires-Dist: OpenEXR (>=1.3.2)
Requires-Dist: termcolor (>=1.1.0)
Requires-Dist: trimesh (>=2.37.22)
Requires-Dist: networkx
